icecube_skyreader-1.6.1.dist-info/licenses/LICENSE
skyreader/__init__.py
skyreader/constants.py
skyreader/event_metadata.py
skyreader/py.typed
skyreader/result.py
skyreader/plot/__init__.py
skyreader/plot/plot.py
skyreader/plot/plotting_tools.py
skyreader/utils/__init__.py
skyreader/utils/areas.py
skyreader/utils/handle_map_data.py
icecube_skyreader-1.6.1.dist-info/METADATA
icecube_skyreader-1.6.1.dist-info/WHEEL
icecube_skyreader-1.6.1.dist-info/top_level.txt
icecube_skyreader-1.6.1.dist-info/RECORD
